samples/project.yaml
src/__about__.py
src/__init_.py
src/cli.py
src/commands.py
src/common.py
src/glossary.py
src/facets/__init__.py
src/facets/code_quality.py
src/facets/pkg_install.py
src/facets/project.py
src/facets/pylint_handler.py
src/facets/repository.py
src/facets/scanner.py
src/helper/__init__.py
src/helper/color_path.py
src/helper/constants.py
src/helper/parser.py
src/helper/utils.py
src/services/__init__.py
src/services/github.py
src/services/local_info.py
templates/.pre-commit-config.yaml
templates/.sourcery.yaml
templates/gitignore.txt
templates/pre_commit.toml
templates/workflow/code-lint.yml
yuhi-0.0.6.dist-info/METADATA
yuhi-0.0.6.dist-info/WHEEL
yuhi-0.0.6.dist-info/entry_points.txt
yuhi-0.0.6.dist-info/licenses/LICENSE
yuhi-0.0.6.dist-info/RECORD
