Metadata-Version: 2.4
Name: yuhi
Version: 0.0.6
Summary: Python CLI toolkit to automate project enhancement using standard config templates.
Project-URL: Docs, https://yuhi.readthedocs.io/
Project-URL: Repository, https://github.com/rsb-23/yuhi
Project-URL: Issues, https://github.com/rsb-23/yuhi/issues
Project-URL: Releases, https://github.com/rsb-23/yuhi/releases
Author-email: Rishabh B <null@example.com>
License-File: LICENSE
Keywords: boilerplate,project,yuhi
Classifier: Development Status :: 4 - Beta
Classifier: Environment :: Console
Classifier: Intended Audience :: Developers
Classifier: License :: OSI Approved :: MIT License
Classifier: Natural Language :: English
Classifier: Operating System :: OS Independent
Classifier: Programming Language :: Python
Classifier: Programming Language :: Python :: 3
Classifier: Programming Language :: Python :: 3.10
Classifier: Programming Language :: Python :: 3.11
Classifier: Programming Language :: Python :: 3.12
Classifier: Programming Language :: Python :: 3.13
Classifier: Programming Language :: Python :: 3.14
Classifier: Programming Language :: Python :: Implementation :: CPython
Requires-Python: >=3.10
Requires-Dist: click
Requires-Dist: httpx
Requires-Dist: questionary
Requires-Dist: ruamel-yaml~=0.18.10
Requires-Dist: toml; python_version < '3.11'
Provides-Extra: lint
Requires-Dist: pre-commit; extra == 'lint'
Requires-Dist: pylint; extra == 'lint'
Provides-Extra: test
Requires-Dist: pytest; extra == 'test'
Requires-Dist: pytest-cov; extra == 'test'
